video_tools/__init__.py
video_tools/__main__.py
video_tools/aggregate.py
video_tools/cli.py
ai4vl_video_tools-0.2.0.dist-info/LICENSE
ai4vl_video_tools-0.2.0.dist-info/METADATA
ai4vl_video_tools-0.2.0.dist-info/WHEEL
ai4vl_video_tools-0.2.0.dist-info/entry_points.txt
ai4vl_video_tools-0.2.0.dist-info/RECORD
