Metadata-Version: 2.1
Name: ai4vl-video-tools
Version: 0.2.0
Summary: 
Author: Felix Rindt
Author-email: felix@rindt.me
Requires-Python: >=3.8,<4.0
Classifier: Programming Language :: Python :: 3
Classifier: Programming Language :: Python :: 3.8
Classifier: Programming Language :: Python :: 3.9
Classifier: Programming Language :: Python :: 3.10
Classifier: Programming Language :: Python :: 3.11
Requires-Dist: awesome-slugify (>=1.6.5,<2.0.0)
Requires-Dist: ffmpeg-python (>=0.2.0,<0.3.0)
Requires-Dist: natsort (>=8.4.0,<9.0.0)
Requires-Dist: tqdm (>=4.65.0,<5.0.0)
